pygame/__init__.py
pygame/__init__.pyi
pygame/_camera.cpython-314-aarch64-linux-gnu.so
pygame/_camera_opencv.py
pygame/_data_classes.py
pygame/_debug.py
pygame/_debug.pyi
pygame/_freetype.cpython-314-aarch64-linux-gnu.so
pygame/_render.cpython-314-aarch64-linux-gnu.so
pygame/_render.pyi
pygame/_sprite.py
pygame/base.cpython-314-aarch64-linux-gnu.so
pygame/base.pyi
pygame/bufferproxy.cpython-314-aarch64-linux-gnu.so
pygame/bufferproxy.pyi
pygame/camera.py
pygame/camera.pyi
pygame/color.cpython-314-aarch64-linux-gnu.so
pygame/color.pyi
pygame/colordict.py
pygame/constants.cpython-314-aarch64-linux-gnu.so
pygame/constants.pyi
pygame/cursors.py
pygame/cursors.pyi
pygame/display.cpython-314-aarch64-linux-gnu.so
pygame/display.pyi
pygame/draw.cpython-314-aarch64-linux-gnu.so
pygame/draw.pyi
pygame/event.cpython-314-aarch64-linux-gnu.so
pygame/event.pyi
pygame/font.cpython-314-aarch64-linux-gnu.so
pygame/font.pyi
pygame/freesansbold.ttf
pygame/freetype.py
pygame/freetype.pyi
pygame/ftfont.py
pygame/geometry.cpython-314-aarch64-linux-gnu.so
pygame/geometry.pyi
pygame/gfxdraw.cpython-314-aarch64-linux-gnu.so
pygame/gfxdraw.pyi
pygame/image.cpython-314-aarch64-linux-gnu.so
pygame/image.pyi
pygame/imageext.cpython-314-aarch64-linux-gnu.so
pygame/joystick.cpython-314-aarch64-linux-gnu.so
pygame/joystick.pyi
pygame/key.cpython-314-aarch64-linux-gnu.so
pygame/key.pyi
pygame/locals.py
pygame/locals.pyi
pygame/macosx.py
pygame/mask.cpython-314-aarch64-linux-gnu.so
pygame/mask.pyi
pygame/math.cpython-314-aarch64-linux-gnu.so
pygame/math.pyi
pygame/midi.py
pygame/midi.pyi
pygame/mixer.cpython-314-aarch64-linux-gnu.so
pygame/mixer.pyi
pygame/mixer_music.cpython-314-aarch64-linux-gnu.so
pygame/mixer_music.pyi
pygame/mouse.cpython-314-aarch64-linux-gnu.so
pygame/mouse.pyi
pygame/newbuffer.cpython-314-aarch64-linux-gnu.so
pygame/pixelarray.cpython-314-aarch64-linux-gnu.so
pygame/pixelarray.pyi
pygame_ce-2.5.5.post1.dist-info/METADATA
pygame_ce-2.5.5.post1.dist-info/WHEEL
pygame_ce-2.5.5.post1.dist-info/entry_points.txt
pygame_ce-2.5.5.post1.dist-info/RECORD
